<annotation>
	<folder>6obj +fondos</folder>
	<filename>22_imgrgb.png</filename>
	<path>/home/patricio/Documentos/src/uch/R-MAC/DBPaper/Evaluacion/6obj/6obj +fondos/22_imgrgb.png</path>
	<source>
		<database>Unknown</database>
	</source>
	<size>
		<width>640</width>
		<height>480</height>
		<depth>3</depth>
	</size>
	<segmented>0</segmented>
	<object>
		<name>balsamo</name>
		<pose>Unspecified</pose>
		<truncated>0</truncated>
		<difficult>0</difficult>
		<bndbox>
			<xmin>195</xmin>
			<ymin>242</ymin>
			<xmax>249</xmax>
			<ymax>335</ymax>
		</bndbox>
	</object>
	<object>
		<name>lata</name>
		<pose>Unspecified</pose>
		<truncated>0</truncated>
		<difficult>0</difficult>
		<bndbox>
			<xmin>224</xmin>
			<ymin>305</ymin>
			<xmax>271</xmax>
			<ymax>374</ymax>
		</bndbox>
	</object>
	<object>
		<name>desodorante</name>
		<pose>Unspecified</pose>
		<truncated>0</truncated>
		<difficult>0</difficult>
		<bndbox>
			<xmin>319</xmin>
			<ymin>326</ymin>
			<xmax>356</xmax>
			<ymax>375</ymax>
		</bndbox>
	</object>
	<object>
		<name>aceite</name>
		<pose>Unspecified</pose>
		<truncated>0</truncated>
		<difficult>0</difficult>
		<bndbox>
			<xmin>238</xmin>
			<ymin>205</ymin>
			<xmax>293</xmax>
			<ymax>314</ymax>
		</bndbox>
	</object>
	<object>
		<name>cloro</name>
		<pose>Unspecified</pose>
		<truncated>0</truncated>
		<difficult>0</difficult>
		<bndbox>
			<xmin>291</xmin>
			<ymin>236</ymin>
			<xmax>354</xmax>
			<ymax>335</ymax>
		</bndbox>
	</object>
	<object>
		<name>confort</name>
		<pose>Unspecified</pose>
		<truncated>0</truncated>
		<difficult>0</difficult>
		<bndbox>
			<xmin>351</xmin>
			<ymin>224</ymin>
			<xmax>466</xmax>
			<ymax>360</ymax>
		</bndbox>
	</object>
</annotation>
